{"sessionStartTime": "2021-12-24 21:03:40.862994-08:00", "sessionEndTime": "2021-12-24 21:04:39.449985-08:00", "sessionDuration": "0:00:58.586991 / 58.586991 seconds", "log": [{"speaker": "ASSISTANT", "text": "Taking speech input...", "tts": false, "time": "2021-12-24 21:03:54.049504"}, {"speaker": "ASSISTANT", "text": "Taking speech input...", "tts": false, "time": "2021-12-24 21:04:14.650068"}, {"speaker": "ASSISTANT", "text": "Taking speech input...", "tts": false, "time": "2021-12-24 21:04:23.251165"}, {"speaker": "ASSISTANT", "text": "Sphinx could not understand audio", "tts": false, "time": "2021-12-24 21:04:25.204916"}, {"speaker": "USER", "text": "search on Yahoo cake recipes", "intEnt": {"intent": "search", "subInt": null, "engine": "yahoo", "term": "cake recipes", "timing": null}, "time": "2021-12-24 21:04:30.857556"}, {"speaker": "ASSISTANT", "text": "Searching on yahoo: cake recipes", "tts": false, "time": "2021-12-24 21:04:31.992009"}]}