{"sessionStartTime": "2021-12-22 11:10:29.599768-08:00", "sessionEndTime": "2021-12-22 11:10:35.650755-08:00", "sessionDuration": "0:00:06.050987 / 6.050987 seconds", "log": [{"speaker": "USER", "text": "help", "intEnt": {"intent": "help", "subInt": null, "timing": null}, "time": "2021-12-22 11:10:31.714190"}, {"speaker": "ASSISTANT", "text": "\tHello!\n\tI am your Virtual Assistant.\n\tI have a number of functions.\n\t\tI can conversate(not well),\n\t\t\t\"Hello!\"\n\t\t\t\"How are you?\"\n\t\tI can tell you about the weather,\n\t\t\t\"How's the weather?\",\n\t\t\t\"Is it humid in Dallas?\",\n\t\t\t\"How does the weather look for the next three days?\"\n\t\tI can help you with things around the house(not actually),\n\t\t\t\"Turn on the lights in the kitchen\",\n\t\t\t\"Set the oven temp to 450 in 5 minutes\",\n\t\t\t\"Turn off all the lights at 6:30\"\n\t\tI can do math for you(like basic arithmetic, sometimes),\n\t\t\t\"What is two plus two?\",\n\t\t\t\"eight divided by 4\",\n\t\t\t\"What is 350 times 29?\"\n\t\tI can make a search on the web for you,\n\t\t\t\"Search on Google cake recipes\",\n\t\t\t\"Search Yahoo for popular tech companies\",\n\t\t\t\"How many satelites are currently in orbit?\"\n\t\tI can open apps on your computer,\n\t\t\t\"Open Discord in seven minutes\",\n\t\t\t\"Open FireFox\",\n\t\t\t\"Please, start up settings\"\n\t\tI can open websites for you,\n\t\t\t\"Go to Youtube\",\n\t\t\t\"Open Google\",\n\t\t\t\"Go to https://www.wired.com/\"\n\t\tI can tell you the time, set timers for you, and tell you long until a certain date,\n\t\t\t\"How many days are there until January 19\",\n\t\t\t\"What time is it?\",\n\t\t\t\"Remind me in an hour to water the plants\"\n\t\tI can tell you a funfact(currently just random, specified topics aren't used),\n\t\t\t\"Tell me a funfact\",\n\t\t\t\"Do you know any cat facts?\",\n\t\t\t\"Tell me a fact about the ISS\"\n\t\tI can generate random numbers,\n\t\t\t\"Give me two random numbers between five and fifteen\",\n\t\t\t\"Roll a 20 sided die, please\",\n\t\t\t\"Flip a coin\"\n\t\tAnd I can play music or grab lyrics from the web.\n\t\t\t\"Play Blinding Lights by The Weeknd\",\n\t\t\t\"What are the lyrics to Woman by Doja Cat?\",\n\t\t\t\"Put on 505 by Arctic Monkeys\"\n", "tts": false, "time": "2021-12-22 11:10:31.742052"}]}